pulumi_dockerbuild/__init__.py
pulumi_dockerbuild/_enums.py
pulumi_dockerbuild/_inputs.py
pulumi_dockerbuild/_utilities.py
pulumi_dockerbuild/image.py
pulumi_dockerbuild/index.py
pulumi_dockerbuild/outputs.py
pulumi_dockerbuild/provider.py
pulumi_dockerbuild/pulumi-plugin.json
pulumi_dockerbuild/py.typed
pulumi_dockerbuild/config/__init__.py
pulumi_dockerbuild/config/__init__.pyi
pulumi_dockerbuild/config/vars.py
pulumi_dockerbuild-0.0.1a2.dist-info/METADATA
pulumi_dockerbuild-0.0.1a2.dist-info/WHEEL
pulumi_dockerbuild-0.0.1a2.dist-info/top_level.txt
pulumi_dockerbuild-0.0.1a2.dist-info/RECORD
