Metadata-Version: 2.1
Name: pulumi_dockerbuild
Version: 0.0.1a2
Summary: A Pulumi provider for Docker buildx
License: Apache-2.0
Project-URL: Homepage, https://pulumi.io
Project-URL: Repository, https://github.com/pulumi/pulumi-dockerbuild
Keywords: docker,buildkit,buildx
Requires-Python: >=3.8
Requires-Dist: parver >=0.2.1
Requires-Dist: pulumi <4.0.0,>=3.0.0
Requires-Dist: semver >=2.8.1
